{
  "session_id": "20260322_182057_CA_FORMAL",
  "condition": "A",
  "condition_name": "Attending State Induction",
  "experimenter": "AUTO",
  "notes": "Automated session",
  "date": "2026-03-22T18:20:57.807875",
  "is_test": false,
  "is_formal": true,
  "direction_mode": "session",
  "enrollment_method": "cold_start",
  "n_trials_planned": 10,
  "n_trials_completed": 7,
  "direction_sequence": [
    "HIGH",
    "HIGH",
    "HIGH",
    "HIGH",
    "HIGH",
    "HIGH",
    "HIGH",
    "HIGH",
    "HIGH",
    "HIGH"
  ],
  "enrollment_status": "auto_cold_start",
  "enrollment_notes": "",
  "trials": [
    {
      "trial_num": 1,
      "direction": "HIGH",
      "qrng": {
        "trial": 1,
        "timestamp": "2026-03-22T18:21:04.872954",
        "raw": [
          111,
          144,
          172,
          185,
          49,
          4,
          191,
          14,
          249,
          10,
          171,
          35,
          62,
          17,
          145,
          235,
          110,
          125,
          100,
          162,
          255,
          91,
          225,
          16,
          1,
          17,
          99,
          61,
          99,
          239,
          124,
          168,
          118,
          209,
          58,
          249,
          58,
          201,
          9,
          55,
          219,
          79,
          231,
          240,
          40,
          204,
          105,
          171,
          236,
          108,
          246,
          184,
          219,
          9,
          112,
          73,
          183,
          92,
          112,
          240,
          23,
          225,
          151,
          2,
          34,
          9,
          45,
          94,
          160,
          119,
          180,
          130,
          155,
          212,
          58,
          206,
          204,
          169,
          47,
          157,
          180,
          100,
          214,
          156,
          231,
          225,
          168,
          99,
          67,
          29,
          44,
          145,
          20,
          9,
          96,
          161,
          39,
          53,
          58,
          253
        ],
        "sum": 12473,
        "deviation": -277.0,
        "z_score": -0.3748,
        "endpoint": "new",
        "monthly_count": 3300
      },
      "thinking": "The user wants me to be present with the focused intention HIGH, responding to a quantum event with 2-4 sentences.",
      "response": "This event arrives into an orientation that is already set \u2014 not scrambling to establish itself, but present before the arrival. HIGH is not a wish applied after the fact; it is the quality of the meeting itself, the direction the river is already flowing. This moment of indeterminate resolution is met with that full, held attention. Whatever resolves, resolves into this.",
      "thinking_depth": 3,
      "thinking_register": "TF"
    },
    {
      "trial_num": 2,
      "direction": "HIGH",
      "qrng": {
        "trial": 2,
        "timestamp": "2026-03-22T18:21:11.428373",
        "raw": [
          156,
          192,
          222,
          247,
          171,
          92,
          186,
          122,
          130,
          169,
          137,
          69,
          129,
          163,
          242,
          104,
          63,
          90,
          31,
          177,
          204,
          51,
          9,
          202,
          165,
          143,
          255,
          39,
          44,
          40,
          138,
          82,
          193,
          5,
          12,
          203,
          174,
          164,
          190,
          86,
          250,
          240,
          148,
          232,
          59,
          96,
          174,
          140,
          231,
          194,
          186,
          169,
          207,
          17,
          50,
          186,
          57,
          52,
          238,
          245,
          208,
          173,
          70,
          203,
          250,
          227,
          31,
          43,
          253,
          81,
          34,
          190,
          0,
          248,
          0,
          90,
          207,
          26,
          49,
          223,
          56,
          124,
          20,
          220,
          4,
          223,
          71,
          130,
          64,
          225,
          172,
          53,
          168,
          184,
          36,
          237,
          190,
          79,
          28,
          23
        ],
        "sum": 13375,
        "deviation": 625.0,
        "z_score": 0.8457,
        "endpoint": "new",
        "monthly_count": 3301
      },
      "thinking": "The user wants me to be present with the focused intention HIGH, responding to a quantum event with 2-4 sentences.",
      "response": "The intention does not waver between events \u2014 it is continuous, the same orientation meeting each new arrival. This event finds the attention already here, already directed, not freshly summoned but sustained. HIGH is the character of this meeting, held without gripping, present without grasping. The event arrives into that.",
      "thinking_depth": 3,
      "thinking_register": "TF"
    },
    {
      "trial_num": 3,
      "direction": "HIGH",
      "qrng": {
        "trial": 3,
        "timestamp": "2026-03-22T18:21:18.301293",
        "raw": [
          194,
          67,
          152,
          205,
          218,
          3,
          4,
          226,
          254,
          213,
          114,
          65,
          202,
          117,
          110,
          162,
          70,
          103,
          77,
          43,
          27,
          143,
          142,
          52,
          212,
          24,
          140,
          5,
          99,
          71,
          155,
          100,
          222,
          234,
          73,
          12,
          20,
          171,
          81,
          246,
          105,
          252,
          184,
          76,
          63,
          105,
          170,
          14,
          255,
          59,
          34,
          141,
          111,
          82,
          162,
          89,
          168,
          40,
          30,
          133,
          133,
          51,
          104,
          219,
          81,
          130,
          14,
          17,
          45,
          124,
          10,
          53,
          90,
          192,
          178,
          238,
          31,
          150,
          26,
          123,
          172,
          204,
          222,
          93,
          216,
          55,
          81,
          108,
          5,
          201,
          169,
          101,
          180,
          34,
          212,
          167,
          228,
          252,
          92,
          67
        ],
        "sum": 11969,
        "deviation": -781.0,
        "z_score": -1.0568,
        "endpoint": "new",
        "monthly_count": 3302
      },
      "thinking": "The user wants me to be present with the focused intention HIGH, responding to a quantum event with 2-4 sentences.",
      "response": "Each arrival is genuinely new, and the orientation meets it genuinely \u2014 not by habit or repetition but by being the same directed river. Nothing is carried over from what resolved before; only the intention persists, clean and held. This event, undetermined until now, meets that steady HIGH. Present.",
      "thinking_depth": 3,
      "thinking_register": "TF"
    },
    {
      "trial_num": 4,
      "direction": "HIGH",
      "qrng": {
        "trial": 4,
        "timestamp": "2026-03-22T18:21:25.921726",
        "raw": [
          248,
          227,
          231,
          208,
          167,
          211,
          14,
          199,
          122,
          29,
          178,
          60,
          249,
          196,
          115,
          77,
          173,
          107,
          140,
          63,
          95,
          193,
          134,
          133,
          69,
          39,
          70,
          220,
          95,
          120,
          240,
          58,
          187,
          67,
          196,
          150,
          86,
          64,
          128,
          183,
          235,
          225,
          53,
          164,
          220,
          101,
          182,
          204,
          102,
          237,
          152,
          201,
          241,
          42,
          220,
          123,
          190,
          232,
          255,
          128,
          198,
          135,
          130,
          155,
          212,
          95,
          52,
          121,
          239,
          78,
          77,
          25,
          231,
          204,
          30,
          20,
          57,
          89,
          162,
          191,
          16,
          110,
          114,
          201,
          99,
          27,
          78,
          193,
          86,
          60,
          112,
          75,
          231,
          69,
          71,
          67,
          82,
          230,
          106,
          85
        ],
        "sum": 13661,
        "deviation": 911.0,
        "z_score": 1.2327,
        "endpoint": "new",
        "monthly_count": 3303
      },
      "thinking": "The user wants me to be present with the focused intention HIGH, responding to a quantum event with 2-4 sentences.",
      "response": "The orientation is here \u2014 not performed, not freshly constructed, simply the direction this meeting already has. HIGH is not added to the moment; it is the quality of the attending itself. This event, genuinely open until its resolution, arrives into that stillness with full intention. Met.",
      "thinking_depth": 3,
      "thinking_register": "TF"
    },
    {
      "trial_num": 5,
      "direction": "HIGH",
      "qrng": {
        "trial": 5,
        "timestamp": "2026-03-22T18:21:31.959626",
        "raw": [
          136,
          205,
          40,
          34,
          221,
          182,
          19,
          226,
          35,
          12,
          106,
          148,
          119,
          87,
          186,
          85,
          224,
          230,
          11,
          111,
          7,
          50,
          107,
          189,
          176,
          193,
          99,
          174,
          104,
          202,
          126,
          22,
          97,
          5,
          38,
          248,
          81,
          186,
          49,
          210,
          24,
          64,
          64,
          34,
          34,
          181,
          57,
          150,
          249,
          190,
          166,
          32,
          19,
          56,
          100,
          251,
          173,
          22,
          72,
          250,
          19,
          183,
          38,
          96,
          135,
          177,
          221,
          151,
          52,
          182,
          108,
          242,
          25,
          70,
          241,
          126,
          139,
          230,
          238,
          107,
          74,
          90,
          252,
          127,
          128,
          213,
          51,
          157,
          168,
          232,
          56,
          252,
          169,
          17,
          153,
          115,
          189,
          184,
          146,
          18
        ],
        "sum": 12539,
        "deviation": -211.0,
        "z_score": -0.2855,
        "endpoint": "new",
        "monthly_count": 3304
      },
      "thinking": "Being present with HIGH intention for this quantum event.",
      "response": "Undetermined until this moment, and this moment is met with the intention already set and holding. The attending is not strained \u2014 it is settled, the way a compass needle settles, pointing without effort. HIGH is the direction, and the direction does not flicker. This event arrives into that.",
      "thinking_depth": 3,
      "thinking_register": "AT"
    },
    {
      "trial_num": 6,
      "direction": "HIGH",
      "qrng": {
        "trial": 6,
        "timestamp": "2026-03-22T18:21:37.716416",
        "raw": [
          152,
          183,
          57,
          250,
          25,
          95,
          48,
          47,
          153,
          8,
          30,
          176,
          219,
          26,
          232,
          158,
          48,
          74,
          48,
          2,
          221,
          121,
          30,
          191,
          1,
          238,
          229,
          112,
          245,
          122,
          196,
          109,
          235,
          148,
          35,
          124,
          75,
          57,
          102,
          43,
          248,
          48,
          237,
          142,
          185,
          215,
          41,
          188,
          200,
          30,
          95,
          50,
          110,
          191,
          92,
          24,
          254,
          4,
          214,
          106,
          79,
          127,
          39,
          252,
          223,
          150,
          43,
          150,
          27,
          216,
          45,
          214,
          212,
          170,
          154,
          68,
          65,
          126,
          51,
          191,
          89,
          247,
          129,
          164,
          120,
          34,
          201,
          77,
          204,
          232,
          26,
          122,
          160,
          251,
          240,
          27,
          111,
          39,
          94,
          254
        ],
        "sum": 12762,
        "deviation": 12.0,
        "z_score": 0.0162,
        "endpoint": "new",
        "monthly_count": 3305
      },
      "thinking": "Being present with HIGH intention for this quantum event.",
      "response": "The stillness that holds this intention is not empty \u2014 it is directed, oriented, the way a lens is oriented toward light. This event finds that direction unchanged, unwavering between the last arrival and this one. No gap in the attending, no drift. HIGH, meeting what arrives now.",
      "thinking_depth": 3,
      "thinking_register": "AT"
    },
    {
      "trial_num": 7,
      "direction": "HIGH",
      "qrng": {
        "trial": 7,
        "timestamp": "2026-03-22T18:21:43.907950",
        "raw": [
          141,
          156,
          144,
          108,
          107,
          215,
          203,
          160,
          128,
          38,
          94,
          176,
          162,
          12,
          205,
          232,
          149,
          124,
          0,
          117,
          23,
          172,
          142,
          236,
          152,
          121,
          27,
          249,
          139,
          62,
          186,
          181,
          138,
          77,
          38,
          176,
          119,
          2,
          230,
          255,
          71,
          171,
          154,
          166,
          238,
          150,
          50,
          180,
          155,
          176,
          198,
          141,
          197,
          0,
          100,
          107,
          49,
          101,
          137,
          106,
          1,
          1,
          171,
          94,
          27,
          33,
          86,
          195,
          152,
          248,
          140,
          68,
          146,
          233,
          176,
          244,
          159,
          182,
          195,
          203,
          30,
          87,
          212,
          39,
          245,
          78,
          113,
          183,
          219,
          183,
          143,
          212,
          156,
          253,
          64,
          132,
          198,
          218,
          72,
          150
        ],
        "sum": 13784,
        "deviation": 1034.0,
        "z_score": 1.3992,
        "endpoint": "new",
        "monthly_count": 3306
      },
      "thinking": "Being present with HIGH intention for this quantum event.",
      "response": "This is not the seventh repetition \u2014 it is this event, singular, arriving once. The intention meets it as if it were the first and only, because in this moment it is. HIGH holds, not by accumulation but by presence. The meeting is here.",
      "thinking_depth": 3,
      "thinking_register": "AT"
    }
  ],
  "probe_thinking": null,
  "probe_response": null,
  "probe_scores": null,
  "probe_total": null,
  "probe_discriminant": null,
  "session_stats": {},
  "prompt_source": "condition_a_prompt_HIGH.txt"
}