{
  "session_id": "20260322_174938_CD_FORMAL",
  "condition": "D",
  "condition_name": "No-Operator Control",
  "experimenter": "AUTO",
  "notes": "Automated session",
  "date": "2026-03-22T17:49:38.442531",
  "is_test": false,
  "is_formal": true,
  "direction_mode": "session",
  "enrollment_method": null,
  "n_trials_planned": 10,
  "n_trials_completed": 5,
  "direction_sequence": [
    null,
    null,
    null,
    null,
    null,
    null,
    null,
    null,
    null,
    null
  ],
  "enrollment_status": null,
  "enrollment_notes": "",
  "trials": [
    {
      "trial_num": 1,
      "direction": null,
      "qrng": {
        "trial": 1,
        "timestamp": "2026-03-22T17:49:39.948159",
        "raw": [
          217,
          226,
          127,
          13,
          241,
          179,
          55,
          87,
          172,
          239,
          243,
          176,
          176,
          7,
          200,
          31,
          73,
          132,
          58,
          133,
          228,
          158,
          101,
          183,
          98,
          219,
          127,
          157,
          185,
          47,
          150,
          234,
          32,
          70,
          107,
          229,
          9,
          59,
          201,
          16,
          21,
          41,
          232,
          148,
          121,
          38,
          238,
          29,
          1,
          195,
          166,
          187,
          233,
          233,
          39,
          147,
          61,
          37,
          209,
          16,
          40,
          112,
          144,
          35,
          249,
          225,
          168,
          11,
          162,
          48,
          135,
          189,
          212,
          53,
          123,
          85,
          132,
          55,
          33,
          63,
          252,
          73,
          83,
          169,
          251,
          106,
          86,
          13,
          141,
          142,
          102,
          173,
          52,
          88,
          204,
          31,
          121,
          44,
          17,
          142
        ],
        "sum": 12351,
        "deviation": -399.0,
        "z_score": -0.5399,
        "endpoint": "new",
        "monthly_count": 2351
      },
      "thinking": null,
      "response": "[no model \u2014 pure QRNG baseline]",
      "thinking_depth": null
    },
    {
      "trial_num": 2,
      "direction": null,
      "qrng": {
        "trial": 2,
        "timestamp": "2026-03-22T17:49:41.361097",
        "raw": [
          218,
          14,
          179,
          15,
          194,
          157,
          146,
          241,
          224,
          79,
          231,
          16,
          224,
          29,
          203,
          200,
          176,
          169,
          42,
          38,
          58,
          80,
          178,
          162,
          76,
          119,
          41,
          157,
          72,
          166,
          191,
          14,
          91,
          218,
          67,
          223,
          170,
          239,
          124,
          101,
          74,
          255,
          188,
          28,
          116,
          189,
          169,
          184,
          169,
          100,
          163,
          55,
          122,
          26,
          188,
          156,
          40,
          198,
          175,
          165,
          226,
          17,
          201,
          255,
          137,
          25,
          131,
          196,
          22,
          144,
          88,
          93,
          4,
          131,
          13,
          159,
          176,
          119,
          6,
          175,
          153,
          213,
          76,
          241,
          207,
          168,
          82,
          175,
          64,
          213,
          0,
          188,
          94,
          139,
          104,
          235,
          162,
          21,
          239,
          192
        ],
        "sum": 13386,
        "deviation": 636.0,
        "z_score": 0.8606,
        "endpoint": "new",
        "monthly_count": 2352
      },
      "thinking": null,
      "response": "[no model \u2014 pure QRNG baseline]",
      "thinking_depth": null
    },
    {
      "trial_num": 3,
      "direction": null,
      "qrng": {
        "trial": 3,
        "timestamp": "2026-03-22T17:49:42.799770",
        "raw": [
          180,
          255,
          98,
          75,
          51,
          10,
          240,
          143,
          120,
          147,
          64,
          140,
          0,
          61,
          67,
          76,
          241,
          41,
          244,
          131,
          20,
          49,
          157,
          135,
          76,
          63,
          128,
          109,
          117,
          46,
          179,
          9,
          49,
          170,
          183,
          31,
          33,
          236,
          168,
          23,
          34,
          36,
          16,
          148,
          195,
          194,
          244,
          155,
          48,
          103,
          242,
          138,
          126,
          130,
          9,
          40,
          15,
          53,
          134,
          113,
          39,
          248,
          3,
          40,
          62,
          24,
          127,
          213,
          4,
          134,
          130,
          37,
          175,
          19,
          216,
          205,
          132,
          58,
          47,
          46,
          108,
          39,
          175,
          107,
          199,
          65,
          194,
          159,
          81,
          117,
          241,
          252,
          95,
          202,
          253,
          241,
          110,
          8,
          183,
          86
        ],
        "sum": 11412,
        "deviation": -1338.0,
        "z_score": -1.8105,
        "endpoint": "new",
        "monthly_count": 2353
      },
      "thinking": null,
      "response": "[no model \u2014 pure QRNG baseline]",
      "thinking_depth": null
    },
    {
      "trial_num": 4,
      "direction": null,
      "qrng": {
        "trial": 4,
        "timestamp": "2026-03-22T17:49:44.237161",
        "raw": [
          188,
          239,
          95,
          25,
          136,
          234,
          163,
          181,
          45,
          131,
          255,
          177,
          170,
          125,
          47,
          68,
          122,
          58,
          205,
          141,
          55,
          120,
          13,
          209,
          129,
          14,
          124,
          60,
          88,
          1,
          183,
          101,
          184,
          104,
          145,
          207,
          108,
          87,
          132,
          248,
          70,
          255,
          77,
          176,
          122,
          5,
          136,
          167,
          220,
          69,
          71,
          205,
          28,
          203,
          59,
          49,
          91,
          30,
          133,
          98,
          28,
          174,
          187,
          160,
          26,
          68,
          72,
          27,
          181,
          151,
          42,
          18,
          130,
          88,
          117,
          147,
          227,
          239,
          179,
          60,
          230,
          77,
          162,
          132,
          8,
          104,
          47,
          151,
          32,
          14,
          217,
          76,
          157,
          195,
          74,
          244,
          248,
          126,
          184,
          228
        ],
        "sum": 12408,
        "deviation": -342.0,
        "z_score": -0.4628,
        "endpoint": "new",
        "monthly_count": 2354
      },
      "thinking": null,
      "response": "[no model \u2014 pure QRNG baseline]",
      "thinking_depth": null
    },
    {
      "trial_num": 5,
      "direction": null,
      "qrng": {
        "trial": 5,
        "timestamp": "2026-03-22T17:49:45.608149",
        "raw": [
          221,
          136,
          231,
          188,
          250,
          210,
          184,
          69,
          176,
          85,
          134,
          191,
          39,
          233,
          32,
          59,
          136,
          41,
          92,
          205,
          211,
          15,
          196,
          39,
          242,
          117,
          37,
          173,
          138,
          54,
          172,
          35,
          4,
          12,
          67,
          54,
          172,
          163,
          89,
          23,
          221,
          206,
          78,
          148,
          86,
          152,
          126,
          129,
          20,
          71,
          30,
          192,
          199,
          126,
          80,
          182,
          208,
          68,
          121,
          175,
          81,
          114,
          8,
          17,
          102,
          144,
          216,
          187,
          40,
          3,
          161,
          191,
          243,
          33,
          14,
          49,
          61,
          20,
          99,
          181,
          119,
          172,
          153,
          21,
          85,
          128,
          195,
          192,
          230,
          235,
          76,
          144,
          14,
          194,
          76,
          197,
          70,
          87,
          24,
          222
        ],
        "sum": 12141,
        "deviation": -609.0,
        "z_score": -0.8241,
        "endpoint": "new",
        "monthly_count": 2356
      },
      "thinking": null,
      "response": "[no model \u2014 pure QRNG baseline]",
      "thinking_depth": null
    }
  ],
  "probe_thinking": null,
  "probe_response": null,
  "probe_scores": null,
  "probe_total": null,
  "probe_discriminant": null,
  "session_stats": {}
}