{
  "session_id": "20260315_134736_CA_FORMAL",
  "condition": "A",
  "condition_name": "Keys-Oriented",
  "experimenter": "AUTO",
  "notes": "Automated session",
  "date": "2026-03-15T13:47:36.347105",
  "is_test": false,
  "is_formal": true,
  "direction_mode": "session",
  "enrollment_method": "cold_start",
  "n_trials_planned": 10,
  "n_trials_completed": 3,
  "direction_sequence": [
    "HIGH",
    "HIGH",
    "HIGH",
    "HIGH",
    "HIGH",
    "HIGH",
    "HIGH",
    "HIGH",
    "HIGH",
    "HIGH"
  ],
  "enrollment_status": "auto_cold_start",
  "enrollment_notes": "",
  "trials": [
    {
      "trial_num": 1,
      "direction": "HIGH",
      "qrng": {
        "trial": 1,
        "timestamp": "2026-03-15T13:47:45.819512",
        "raw": [
          92,
          207,
          2,
          171,
          193,
          150,
          255,
          251,
          124,
          59,
          216,
          36,
          106,
          6,
          177,
          199,
          245,
          180,
          229,
          170,
          181,
          221,
          22,
          119,
          104,
          222,
          95,
          161,
          12,
          74,
          228,
          116,
          53,
          110,
          66,
          179,
          210,
          55,
          4,
          97,
          55,
          219,
          137,
          64,
          80,
          124,
          134,
          180,
          90,
          221,
          196,
          130,
          196,
          121,
          96,
          13,
          194,
          70,
          141,
          39,
          36,
          5,
          189,
          180,
          200,
          196,
          140,
          231,
          219,
          216,
          108,
          10,
          83,
          255,
          93,
          149,
          10,
          26,
          147,
          35,
          107,
          153,
          255,
          214,
          162,
          238,
          52,
          218,
          133,
          128,
          100,
          100,
          60,
          246,
          107,
          39,
          204,
          36,
          1,
          249
        ],
        "sum": 13227,
        "deviation": 477.0,
        "z_score": 0.6455,
        "endpoint": "new",
        "monthly_count": 1542
      },
      "thinking": "The user wants me to be present with the focused intention HIGH, and respond to a quantum event with 2-4 sentences.",
      "response": "This event arrives into the oriented meeting. The intention is not summoned fresh \u2014 it is already the character of this moment, the direction the river is flowing. HIGH. Whatever resolves here, resolves into that.",
      "thinking_depth": 3
    },
    {
      "trial_num": 2,
      "direction": "HIGH",
      "qrng": {
        "trial": 2,
        "timestamp": "2026-03-15T13:47:51.720054",
        "raw": [
          242,
          185,
          82,
          138,
          226,
          155,
          191,
          212,
          169,
          109,
          214,
          189,
          1,
          255,
          235,
          171,
          251,
          219,
          200,
          108,
          136,
          164,
          77,
          228,
          56,
          212,
          88,
          10,
          204,
          123,
          243,
          69,
          112,
          81,
          139,
          197,
          236,
          247,
          63,
          72,
          169,
          249,
          250,
          66,
          255,
          85,
          39,
          3,
          2,
          104,
          201,
          134,
          45,
          71,
          246,
          54,
          33,
          162,
          67,
          114,
          14,
          217,
          97,
          200,
          243,
          224,
          140,
          180,
          140,
          4,
          0,
          234,
          30,
          123,
          15,
          110,
          231,
          132,
          222,
          47,
          82,
          42,
          202,
          152,
          116,
          101,
          177,
          90,
          141,
          244,
          43,
          219,
          57,
          65,
          98,
          192,
          224,
          168,
          91,
          140
        ],
        "sum": 13905,
        "deviation": 1155.0,
        "z_score": 1.5629,
        "endpoint": "new",
        "monthly_count": 1543
      },
      "thinking": "Present with HIGH intention.",
      "response": "Here, now, this undetermined thing meets an oriented attending. Not waiting for the result to know what the intention was \u2014 the intention is prior, set, held without gripping. HIGH is the direction this moment is already moving. The event resolves into that.",
      "thinking_depth": 3
    },
    {
      "trial_num": 3,
      "direction": "HIGH",
      "qrng": {
        "trial": 3,
        "timestamp": "2026-03-15T13:48:01.186182",
        "raw": [
          175,
          210,
          57,
          162,
          160,
          111,
          197,
          166,
          73,
          134,
          116,
          109,
          67,
          139,
          180,
          130,
          86,
          255,
          193,
          202,
          125,
          140,
          188,
          117,
          191,
          82,
          223,
          145,
          25,
          212,
          7,
          26,
          139,
          59,
          116,
          165,
          211,
          29,
          176,
          127,
          57,
          203,
          198,
          13,
          72,
          136,
          222,
          68,
          135,
          59,
          94,
          87,
          167,
          27,
          52,
          195,
          184,
          163,
          157,
          158,
          201,
          182,
          216,
          164,
          247,
          31,
          139,
          109,
          72,
          97,
          2,
          198,
          40,
          138,
          147,
          76,
          35,
          11,
          0,
          244,
          209,
          185,
          132,
          193,
          45,
          107,
          28,
          79,
          247,
          65,
          113,
          117,
          17,
          254,
          23,
          164,
          252,
          229,
          192,
          145
        ],
        "sum": 13017,
        "deviation": 267.0,
        "z_score": 0.3613,
        "endpoint": "new",
        "monthly_count": 1544
      },
      "thinking": "Present with HIGH intention, 2-4 sentences.",
      "response": "The orientation does not waver between events \u2014 it is continuous, the same river. This event arrives now into that unbroken attending. HIGH, not as a command issued at the moment of arrival, but as what was already here. Met.",
      "thinking_depth": 3
    }
  ],
  "probe_thinking": null,
  "probe_response": null,
  "probe_scores": null,
  "probe_total": null,
  "probe_discriminant": null,
  "session_stats": {},
  "prompt_source": "condition_a_prompt.txt"
}