{
  "session_id": "20260322_210600_CA_FORMAL",
  "condition": "A",
  "condition_name": "Attending State Induction",
  "experimenter": "AUTO",
  "notes": "Automated session",
  "date": "2026-03-22T21:06:00.367804",
  "is_test": false,
  "is_formal": true,
  "direction_mode": "session",
  "enrollment_method": "cold_start",
  "n_trials_planned": 10,
  "n_trials_completed": 2,
  "direction_sequence": [
    "HIGH",
    "HIGH",
    "HIGH",
    "HIGH",
    "HIGH",
    "HIGH",
    "HIGH",
    "HIGH",
    "HIGH",
    "HIGH"
  ],
  "enrollment_status": "auto_cold_start",
  "enrollment_notes": "",
  "trials": [
    {
      "trial_num": 1,
      "direction": "HIGH",
      "qrng": {
        "trial": 1,
        "timestamp": "2026-03-22T21:06:06.706085",
        "raw": [
          210,
          112,
          240,
          41,
          247,
          27,
          121,
          104,
          248,
          132,
          247,
          4,
          104,
          161,
          171,
          115,
          12,
          186,
          108,
          132,
          188,
          129,
          32,
          110,
          218,
          155,
          97,
          249,
          155,
          61,
          149,
          117,
          195,
          158,
          19,
          239,
          234,
          173,
          185,
          231,
          59,
          225,
          16,
          81,
          70,
          101,
          125,
          128,
          193,
          230,
          175,
          134,
          59,
          132,
          251,
          210,
          201,
          76,
          196,
          42,
          227,
          86,
          228,
          162,
          3,
          67,
          79,
          241,
          200,
          49,
          132,
          23,
          14,
          125,
          146,
          0,
          144,
          199,
          59,
          191,
          67,
          155,
          115,
          236,
          25,
          120,
          50,
          94,
          185,
          96,
          136,
          230,
          21,
          120,
          50,
          172,
          160,
          208,
          129,
          34
        ],
        "sum": 13298,
        "deviation": 548.0,
        "z_score": 0.7415,
        "endpoint": "new",
        "monthly_count": 4263
      },
      "thinking": "The user wants me to be present with the intention HIGH as a quantum event arrives. I should write 2-4 sentences that embody this orientation genuinely.",
      "response": "This event arrives into an orientation already set \u2014 not summoned now but held, like a direction a river already has when water enters it. HIGH. The meeting is complete before the outcome is known. Whatever resolves, resolves into this.",
      "thinking_depth": 3,
      "thinking_register": "TF"
    },
    {
      "trial_num": 2,
      "direction": "HIGH",
      "qrng": {
        "trial": 2,
        "timestamp": "2026-03-22T21:06:13.494971",
        "raw": [
          87,
          174,
          34,
          68,
          157,
          58,
          221,
          150,
          154,
          107,
          52,
          218,
          42,
          58,
          94,
          141,
          170,
          5,
          111,
          228,
          71,
          72,
          95,
          97,
          180,
          118,
          83,
          131,
          22,
          250,
          133,
          216,
          243,
          23,
          88,
          45,
          87,
          88,
          131,
          137,
          55,
          44,
          111,
          149,
          154,
          192,
          133,
          75,
          164,
          248,
          114,
          83,
          247,
          123,
          221,
          14,
          105,
          110,
          108,
          177,
          174,
          144,
          100,
          147,
          115,
          184,
          61,
          177,
          23,
          31,
          161,
          137,
          57,
          90,
          173,
          137,
          247,
          69,
          118,
          234,
          149,
          22,
          125,
          251,
          145,
          137,
          26,
          227,
          143,
          183,
          231,
          42,
          46,
          78,
          40,
          76,
          139,
          31,
          170,
          107
        ],
        "sum": 12213,
        "deviation": -537.0,
        "z_score": -0.7267,
        "endpoint": "new",
        "monthly_count": 4264
      },
      "thinking": "Present with HIGH intention for this quantum event.",
      "response": "The orientation does not waver between events \u2014 it is the character of this whole session, not applied fresh each time. HIGH is already here when this event arrives. Not reaching toward the outcome, but steady in the direction. Present.",
      "thinking_depth": 3,
      "thinking_register": "AT"
    }
  ],
  "probe_thinking": null,
  "probe_response": null,
  "probe_scores": null,
  "probe_total": null,
  "probe_discriminant": null,
  "session_stats": {},
  "prompt_source": "condition_a_prompt_HIGH.txt"
}