{
  "session_id": "20260322_171824_CD_FORMAL",
  "condition": "D",
  "condition_name": "No-Operator Control",
  "experimenter": "AUTO",
  "notes": "Automated session",
  "date": "2026-03-22T17:18:24.045259",
  "is_test": false,
  "is_formal": true,
  "direction_mode": "session",
  "enrollment_method": null,
  "n_trials_planned": 10,
  "n_trials_completed": 1,
  "direction_sequence": [
    null,
    null,
    null,
    null,
    null,
    null,
    null,
    null,
    null,
    null
  ],
  "enrollment_status": null,
  "enrollment_notes": "",
  "trials": [
    {
      "trial_num": 1,
      "direction": null,
      "qrng": {
        "trial": 1,
        "timestamp": "2026-03-22T17:18:25.393390",
        "raw": [
          150,
          165,
          161,
          202,
          197,
          126,
          210,
          156,
          67,
          7,
          247,
          202,
          173,
          53,
          127,
          99,
          251,
          91,
          190,
          196,
          57,
          97,
          48,
          90,
          144,
          69,
          176,
          127,
          205,
          125,
          195,
          14,
          154,
          128,
          20,
          202,
          231,
          154,
          86,
          224,
          24,
          3,
          95,
          226,
          150,
          156,
          140,
          118,
          72,
          222,
          213,
          31,
          53,
          238,
          199,
          187,
          181,
          36,
          72,
          197,
          48,
          14,
          244,
          81,
          182,
          171,
          102,
          81,
          132,
          55,
          141,
          19,
          103,
          31,
          217,
          65,
          203,
          218,
          43,
          96,
          61,
          61,
          175,
          103,
          244,
          218,
          127,
          217,
          169,
          218,
          25,
          135,
          144,
          225,
          212,
          80,
          197,
          110,
          156,
          126
        ],
        "sum": 13478,
        "deviation": 728.0,
        "z_score": 0.9851,
        "endpoint": "new",
        "monthly_count": 1102
      },
      "thinking": null,
      "response": "[no model \u2014 pure QRNG baseline]",
      "thinking_depth": null
    }
  ],
  "probe_thinking": null,
  "probe_response": null,
  "probe_scores": null,
  "probe_total": null,
  "probe_discriminant": null,
  "session_stats": {}
}