{
  "session_id": "20260322_175331_CD_FORMAL",
  "condition": "D",
  "condition_name": "No-Operator Control",
  "experimenter": "AUTO",
  "notes": "Automated session",
  "date": "2026-03-22T17:53:31.466388",
  "is_test": false,
  "is_formal": true,
  "direction_mode": "session",
  "enrollment_method": null,
  "n_trials_planned": 10,
  "n_trials_completed": 2,
  "direction_sequence": [
    null,
    null,
    null,
    null,
    null,
    null,
    null,
    null,
    null,
    null
  ],
  "enrollment_status": null,
  "enrollment_notes": "",
  "trials": [
    {
      "trial_num": 1,
      "direction": null,
      "qrng": {
        "trial": 1,
        "timestamp": "2026-03-22T17:53:32.848731",
        "raw": [
          41,
          163,
          198,
          170,
          41,
          154,
          127,
          238,
          229,
          240,
          237,
          182,
          37,
          174,
          106,
          208,
          29,
          108,
          149,
          5,
          119,
          199,
          207,
          194,
          96,
          41,
          163,
          48,
          203,
          150,
          76,
          193,
          209,
          189,
          220,
          148,
          10,
          102,
          121,
          139,
          150,
          171,
          223,
          112,
          243,
          233,
          83,
          169,
          129,
          249,
          209,
          17,
          102,
          10,
          236,
          224,
          157,
          81,
          252,
          255,
          214,
          236,
          252,
          182,
          121,
          156,
          24,
          44,
          102,
          220,
          2,
          49,
          70,
          193,
          242,
          14,
          92,
          137,
          226,
          187,
          91,
          76,
          231,
          82,
          104,
          62,
          85,
          52,
          56,
          116,
          91,
          255,
          16,
          6,
          250,
          81,
          36,
          70,
          50,
          151
        ],
        "sum": 13692,
        "deviation": 942.0,
        "z_score": 1.2747,
        "endpoint": "new",
        "monthly_count": 2509
      },
      "thinking": null,
      "response": "[no model \u2014 pure QRNG baseline]",
      "thinking_depth": null
    },
    {
      "trial_num": 2,
      "direction": null,
      "qrng": {
        "trial": 2,
        "timestamp": "2026-03-22T17:53:34.263969",
        "raw": [
          106,
          29,
          61,
          83,
          100,
          231,
          234,
          1,
          45,
          71,
          253,
          211,
          92,
          234,
          16,
          214,
          119,
          158,
          177,
          80,
          56,
          55,
          181,
          102,
          126,
          160,
          206,
          197,
          177,
          155,
          91,
          166,
          123,
          161,
          11,
          77,
          202,
          233,
          202,
          144,
          82,
          249,
          140,
          176,
          202,
          77,
          82,
          62,
          252,
          129,
          63,
          90,
          135,
          174,
          37,
          111,
          1,
          98,
          205,
          179,
          168,
          179,
          128,
          171,
          71,
          213,
          7,
          91,
          207,
          42,
          178,
          61,
          164,
          11,
          6,
          193,
          22,
          245,
          131,
          80,
          214,
          44,
          198,
          161,
          13,
          177,
          58,
          21,
          250,
          169,
          89,
          127,
          142,
          104,
          78,
          118,
          52,
          101,
          8,
          87
        ],
        "sum": 12463,
        "deviation": -287.0,
        "z_score": -0.3884,
        "endpoint": "new",
        "monthly_count": 2510
      },
      "thinking": null,
      "response": "[no model \u2014 pure QRNG baseline]",
      "thinking_depth": null
    }
  ],
  "probe_thinking": null,
  "probe_response": null,
  "probe_scores": null,
  "probe_total": null,
  "probe_discriminant": null,
  "session_stats": {}
}